{
  "order": {
    "ordernummer": "2019-895",
    "orderdatum": "03-07-2023",
    "betaaltermijn": "90-dagen",
    "klant": {
      "naam": "PC Jupiter B.V.",
      "adres": "Hoofdstraat 603",
      "postcode": "1933 AA",
      "stad": "Utrecht",
      "KVK-nummer": "65736258"
    },
    "producten": [
      {
        "productnaam": "Microsoft Windows 10",
        "aantal": 5,
        "prijs_per_stuk_excl_btw": 304.22,
        "btw_percentage": 9
      },
      {
        "productnaam": "Microsoft SQL Server 2019",
        "aantal": 4,
        "prijs_per_stuk_excl_btw": 155.12,
        "btw_percentage": 6
      },
      {
        "productnaam": "Adobe InDesign",
        "aantal": 1,
        "prijs_per_stuk_excl_btw": 389.68,
        "btw_percentage": 9
      }
    ]
  }
}